zzhfun/__init__.py
zzhfun/core.py
zzhfun/uni_variable_analysis.py
zzhfun/Eval/BaseMetric.py
zzhfun/Eval/CfMetric.py
zzhfun/Eval/Metric.py
zzhfun/Eval/PSI.py
zzhfun/Eval/__init__.py
zzhfun-0.30.dist-info/METADATA
zzhfun-0.30.dist-info/WHEEL
zzhfun-0.30.dist-info/top_level.txt
zzhfun-0.30.dist-info/RECORD
