Metadata-Version: 2.1
Name: zzhfun
Version: 0.30
Summary: zzh model function and data function
Home-page: https://github.com/FlashSnail/zzhfun
Author: Zzh
Author-email: zzh_0729@foxmail.com
License: UNKNOWN
Platform: UNKNOWN
Classifier: Programming Language :: Python :: 3
Classifier: Programming Language :: Python :: 2
Classifier: License :: OSI Approved :: MIT License
Classifier: Operating System :: OS Independent
Requires-Dist: pandas (>=0.24.2)
Requires-Dist: numpy (>=1.16.2)
Requires-Dist: xgboost (>=0.82)
Requires-Dist: scikit-learn (<=0.20.3)
